{
  "templates": {
    "2": [
      {
        "name": "Dev - 2",
        "roles": {
          "AdamSnowman": 0,
          "Afyun": 0,
          "AlCapone": 0,
          "Avenger": 0,
          "Bartender": 0,
          "Bisim chi": 0,
          "Blacksmith": 0,
          "Bomber": 0,
          "Butcher": 0,
          "Buyer": 0,
          "Carrier": 0,
          "CitizenSpecialist": 0,
          "CodeWriter": 0,
          "Commander": 0,
          "Corona": 0,
          "Cowboy": 0,
          "Doctor": 1,
          "DoctorLec": 0,
          "Doppelganger": 0,
          "DoubleFace": 0,
          "Dynamite": 0,
          "Efsha Gar": 0,
          "Elite": 0,
          "Enchanter": 0,
          "Executioner": 0,
          "Exposer": 0,
          "Freemason": 0,
          "Gambler": 0,
          "Ghazi": 0,
          "God F": 0,
          "Gor Kan": 0,
          "Guardian": 0,
          "Gunsmith": 0,
          "Hacker": 0,
          "Hunter": 0,
          "Inquisitor": 0,
          "Investigator": 0,
          "JackSparrow": 0,
          "Jasoos": 0,
          "Jigsaw": 0,
          "Joker": 0,
          "Judge": 0,
          "Jupiter": 0,
          "Kar Agah": 0,
          "Keshish": 0,
          "Killer": 0,
          "LadyVoodoo": 0,
          "Link": 0,
          "MafiaSa": 0,
          "MafiaSpecialist": 0,
          "Majhool": 0,
          "Mashoghe": 0,
          "MaskedFigure": 0,
          "Mozakere": 0,
          "MunitionsExpert": 0,
          "NamelessMafia": 0,
          "Nanva": 0,
          "Natasha": 0,
          "NightWanderer": 0,
          "NightWatch": 0,
          "Ocean": 0,
          "Physician": 0,
          "PoisonMaker": 0,
          "PoliceChief": 0,
          "Priest": 0,
          "Revealer": 0,
          "Ronan": 0,
          "RussianRoulette": 0,
          "Ruyin tan": 0,
          "Saba": 0,
          "Saboteur": 0,
          "Sacrifice": 0,
          "Scribe": 0,
          "ShahKosh": 0,
          "ShahrSaD": 1,
          "Sheriff": 0,
          "SherlockHolmes": 0,
          "Sniper": 0,
          "Spider": 0,
          "Spy": 0,
          "StrongMan": 0,
          "Swordsman": 0,
          "Syndicate": 0,
          "Tak Tir": 0,
          "Terrorist": 0,
          "Thief": 0,
          "ThousandFace": 0,
          "Tof Dar": 0,
          "ToughGuy": 0,
          "Trickster": 0,
          "Tyler": 0,
          "Unknown": 0,
          "Werewolf": 0,
          "WiseMan": 0,
          "Wizard": 0,
          "Yakuza": 0,
          "Zodiac": 0
        }
      },
      {
        "name": "Devi - 2",
        "roles": {
          "AdamSnowman": 0,
          "Afyun": 0,
          "AlCapone": 0,
          "Avenger": 0,
          "Bartender": 0,
          "Bisim chi": 0,
          "Blacksmith": 0,
          "Bomber": 0,
          "Butcher": 0,
          "Buyer": 0,
          "Carrier": 0,
          "CitizenSpecialist": 0,
          "CodeWriter": 0,
          "Commander": 0,
          "Corona": 0,
          "Cowboy": 0,
          "Doctor": 0,
          "DoctorLec": 0,
          "Doppelganger": 0,
          "DoubleFace": 0,
          "Dynamite": 0,
          "Efsha Gar": 0,
          "Elite": 0,
          "Enchanter": 0,
          "Executioner": 0,
          "Exposer": 0,
          "Freemason": 0,
          "Gambler": 0,
          "Ghazi": 0,
          "God F": 1,
          "Gor Kan": 0,
          "Guardian": 0,
          "Gunsmith": 0,
          "Hacker": 0,
          "Hunter": 0,
          "Inquisitor": 0,
          "Investigator": 0,
          "JackSparrow": 0,
          "Jasoos": 0,
          "Jigsaw": 0,
          "Joker": 0,
          "Judge": 0,
          "Jupiter": 0,
          "Kar Agah": 0,
          "Keshish": 0,
          "Killer": 0,
          "LadyVoodoo": 0,
          "Link": 0,
          "MafiaSa": 0,
          "MafiaSpecialist": 0,
          "Majhool": 0,
          "Mashoghe": 0,
          "MaskedFigure": 0,
          "Mozakere": 0,
          "MunitionsExpert": 0,
          "NamelessMafia": 0,
          "Nanva": 0,
          "Natasha": 0,
          "NightWanderer": 0,
          "NightWatch": 0,
          "Ocean": 0,
          "Physician": 0,
          "PoisonMaker": 0,
          "PoliceChief": 0,
          "Priest": 0,
          "Revealer": 0,
          "Ronan": 0,
          "RussianRoulette": 0,
          "Ruyin tan": 0,
          "Saba": 0,
          "Saboteur": 0,
          "Sacrifice": 0,
          "Scribe": 0,
          "ShahKosh": 0,
          "ShahrSaD": 1,
          "Sheriff": 0,
          "SherlockHolmes": 0,
          "Sniper": 0,
          "Spider": 0,
          "Spy": 0,
          "StrongMan": 0,
          "Swordsman": 0,
          "Syndicate": 0,
          "Tak Tir": 0,
          "Terrorist": 0,
          "Thief": 0,
          "ThousandFace": 0,
          "Tof Dar": 0,
          "ToughGuy": 0,
          "Trickster": 0,
          "Tyler": 0,
          "Unknown": 0,
          "Werewolf": 0,
          "WiseMan": 0,
          "Wizard": 0,
          "Yakuza": 0,
          "Zodiac": 0
        }
      }
    ]
  },
  "pending_templates": {
    "2": []
  }
}